.coveragerc
.gitlab-ci.yml
.gitmodules
AUTHORS
AUTHORS.rst
ChangeLog
LICENSE
MANIFEST.in
README.rst
bootstrap
requirements.txt
run-tests.sh
setup.cfg
setup.py
teuthology
tox.ini
bin/ceph-workbench
ceph_workbench/__init__.py
ceph_workbench/ceph_qa_suite.py
ceph_workbench/delegate.py
ceph_workbench/main.py
ceph_workbench/release.py
ceph_workbench/util.py
ceph_workbench/wbbackport.py
ceph_workbench/wbbackportcreateissue.py
ceph_workbench/wbbackportsetrelease.py
ceph_workbench/wbgit.py
ceph_workbench/wbgithub.py
ceph_workbench/wbgitlab.py
ceph_workbench/wbredmine.py
ceph_workbench/wbxref.py
ceph_workbench.egg-info/PKG-INFO
ceph_workbench.egg-info/SOURCES.txt
ceph_workbench.egg-info/dependency_links.txt
ceph_workbench.egg-info/requires.txt
ceph_workbench.egg-info/top_level.txt
data_files/create-qemu-img
data_files/docker-make-check-bot
data_files/make-check-bot
data_files/libguestfs-docker/Dockerfile
docker/Dockerfile
docker/entrypoint.sh
docs/MANIFEST.in
docs/conf.py
docs/index.rst
docs/_static/forkme.png
docs/_static/monster.png
docs/_templates/sidebarintro.html
docs/_templates/sidebarlogo.html
docs/_themes/.gitignore
docs/_themes/LICENSE
docs/_themes/README.rst
docs/_themes/flask_theme_support.py
docs/_themes/kr/layout.html
docs/_themes/kr/relations.html
docs/_themes/kr/theme.conf
docs/_themes/kr/static/flasky.css_t
docs/_themes/kr_small/layout.html
docs/_themes/kr_small/theme.conf
docs/_themes/kr_small/static/flasky.css_t
docs/dev/authors.rst
docs/dev/namespace.rst
docs/dev/philosophy.rst
tests/fixture_git.py
tests/fixture_github.py
tests/fixture_gitlab.py
tests/fixture_redmine.py
tests/fixture_xref.py
tests/redmine-init.py
tests/setup-ceph-fixture.sh
tests/setup-gitlab.sh
tests/setup-redmine.sh
tests/setup.sh
tests/teardown.sh
tests/test_ceph_qa_suite.py
tests/test_delegate.py
tests/test_main.py
tests/test_release.py
tests/test_util.py
tests/test_wbbackport.py
tests/test_wbbackportcreateissue.py
tests/test_wbbackportsetrelease.py
tests/test_wbgit.py
tests/test_wbgithub.py
tests/test_wbgitlab.py
tests/test_wbredmine.py
tests/test_wbxref.py
tests/ceph-fixture/ChangeLog
tests/ceph-fixture/Makefile.am
tests/ceph-fixture/README.md
