Metadata-Version: 1.1
Name: ceph-workbench
Version: 1.5.19
Summary: a command-line toolbox for Ceph
Home-page: http://ceph-workbench.dachary.org/root/ceph-workbench
Author: Loic Dachary
Author-email: loic@dachary.org
License: UNKNOWN
Platform: UNKNOWN
Classifier: Environment :: Console
Classifier: Intended Audience :: Information Technology
Classifier: Intended Audience :: System Administrators
Classifier: Operating System :: POSIX :: Linux
Classifier: License :: OSI Approved :: GNU General Public License v3 or later (GPLv3+)
Classifier: Programming Language :: Python
Classifier: Programming Language :: Python :: 2
Classifier: Programming Language :: Python :: 3
Classifier: Topic :: Utilities
